[
  {
    "id": "aespa-tokyo-2026",
    "artist": "aespa",
    "artistSlug": "aespa",
    "slug": "aespa-tokyo-2026",
    "city": "Tokyo",
    "country": "Japan",
    "venue": "Ariake Arena",
    "startDate": "2026-03-29T18:30:00+09:00",
    "timezone": "Asia/Tokyo",
    "status": "sold_out",
    "source": "aespa official channel",
    "sourceUrl": "https://weverse.io/aespa",
    "sourceConfidence": "official",
    "tags": [
      "Japan",
      "Arena",
      "Waitlist"
    ],
    "title": "aespa in Tokyo",
    "tourName": "aespa Tour Watch",
    "description": "aespa 的 Tokyo 场会把官宣入口、购票说明、场馆交通和中文观演决策放在一起。",
    "purchaseHint": "官方转售和补票机制往往比二级票更安全。",
    "priceNote": "日本场常见会员抽选与多轮补票。",
    "travelNote": "适合在页内补电子票、返程和周边住宿建议。",
    "checklist": [
      "关注官方补票",
      "确认电子票取票方式",
      "留意转售合法性"
    ],
    "heroImage": "/media/events/aespa-tokyo-2026.svg",
    "ticketLinks": [
      {
        "label": "aespa Official",
        "href": "https://weverse.io/aespa",
        "type": "official"
      }
    ]
  },
  {
    "id": "seventeen-seoul-2026",
    "artist": "SEVENTEEN",
    "artistSlug": "seventeen",
    "slug": "seventeen-seoul-2026",
    "city": "Seoul",
    "country": "South Korea",
    "venue": "KSPO Dome",
    "startDate": "2026-04-18T19:00:00+09:00",
    "timezone": "Asia/Seoul",
    "status": "on_sale",
    "source": "SEVENTEEN official channel",
    "sourceUrl": "https://weverse.io/seventeen",
    "sourceConfidence": "official",
    "tags": [
      "World Tour",
      "Korea",
      "Membership"
    ],
    "title": "SEVENTEEN in Seoul",
    "tourName": "SEVENTEEN Tour Watch",
    "description": "SEVENTEEN 的 Seoul 场会把官宣入口、购票说明、场馆交通和中文观演决策放在一起。",
    "purchaseHint": "CARAT 会员预售通常需要先完成认证。",
    "priceNote": "优先比较 Floor、Stand 和福利票规则。",
    "travelNote": "演出日人流很大，住宿和返程最好围绕 5 号线或 9 号线安排。",
    "checklist": [
      "确认实名规则",
      "确认预售认证时间",
      "准备支付方式"
    ],
    "heroImage": "/media/events/seventeen-seoul-2026.svg",
    "ticketLinks": [
      {
        "label": "SEVENTEEN Official",
        "href": "https://weverse.io/seventeen",
        "type": "official"
      }
    ]
  },
  {
    "id": "j-hope-seoul-2026",
    "artist": "j-hope",
    "artistSlug": "j-hope",
    "slug": "j-hope-seoul-2026",
    "city": "Seoul",
    "country": "South Korea",
    "venue": "Jamsil Indoor Stadium",
    "startDate": "2026-04-26T18:00:00+09:00",
    "timezone": "Asia/Seoul",
    "status": "announced",
    "source": "j-hope official channel",
    "sourceUrl": "https://weverse.io/jhope",
    "sourceConfidence": "official",
    "tags": [
      "Solo",
      "Korea",
      "Membership"
    ],
    "title": "j-hope in Seoul",
    "tourName": "j-hope Tour Watch",
    "description": "j-hope 的 Seoul 场会把官宣入口、购票说明、场馆交通和中文观演决策放在一起。",
    "purchaseHint": "先确认会员预售与公开发售的时间差。",
    "priceNote": "solo 场常见福利票和限购规则。",
    "travelNote": "蚕室一带散场后叫车难度高，建议优先地铁。",
    "checklist": [
      "准备 Weverse 账号",
      "确认实名信息",
      "预留返程时间"
    ],
    "heroImage": "/media/events/j-hope-seoul-2026.svg",
    "ticketLinks": [
      {
        "label": "j-hope Official",
        "href": "https://weverse.io/jhope",
        "type": "official"
      }
    ]
  },
  {
    "id": "txt-osaka-2026",
    "artist": "TOMORROW X TOGETHER",
    "artistSlug": "txt",
    "slug": "txt-osaka-2026",
    "city": "Osaka",
    "country": "Japan",
    "venue": "Kyocera Dome Osaka",
    "startDate": "2026-05-03T18:00:00+09:00",
    "timezone": "Asia/Tokyo",
    "status": "announced",
    "source": "TOMORROW X TOGETHER official channel",
    "sourceUrl": "https://weverse.io/txt",
    "sourceConfidence": "official",
    "tags": [
      "Japan",
      "Dome",
      "MOA"
    ],
    "title": "TOMORROW X TOGETHER in Osaka",
    "tourName": "TOMORROW X TOGETHER Tour Watch",
    "description": "TOMORROW X TOGETHER 的 Osaka 场会把官宣入口、购票说明、场馆交通和中文观演决策放在一起。",
    "purchaseHint": "日本巨蛋场优先看抽选和发券节点。",
    "priceNote": "日本大场多轮抽选的支付和取票方式会不同。",
    "travelNote": "大阪场适合补周边住宿和散场交通。",
    "checklist": [
      "确认抽选轮次",
      "核对电子票规则",
      "预订返程列车"
    ],
    "heroImage": "/media/events/txt-osaka-2026.svg",
    "ticketLinks": [
      {
        "label": "TOMORROW X TOGETHER Official",
        "href": "https://weverse.io/txt",
        "type": "official"
      }
    ]
  },
  {
    "id": "blackpink-los-angeles-2026",
    "artist": "BLACKPINK",
    "artistSlug": "blackpink",
    "slug": "blackpink-los-angeles-2026",
    "city": "Los Angeles",
    "country": "United States",
    "venue": "BMO Stadium",
    "startDate": "2026-05-09T20:00:00-07:00",
    "timezone": "America/Los_Angeles",
    "status": "announced",
    "source": "BLACKPINK official channel",
    "sourceUrl": "https://www.blackpinkmusic.com/",
    "sourceConfidence": "official",
    "tags": [
      "North America",
      "Stadium",
      "Presale"
    ],
    "title": "BLACKPINK in Los Angeles",
    "tourName": "BLACKPINK Tour Watch",
    "description": "BLACKPINK 的 Los Angeles 场会把官宣入口、购票说明、场馆交通和中文观演决策放在一起。",
    "purchaseHint": "先判断自己能否进入官方、平台或信用卡预售。",
    "priceNote": "体育场票价跨度大，别只看票面价格。",
    "travelNote": "BMO Stadium 演出日停车和网约车压力都很高。",
    "checklist": [
      "确认 presale code 来源",
      "比较座位区块",
      "预留停车预算"
    ],
    "heroImage": "/media/events/blackpink-los-angeles-2026.svg",
    "ticketLinks": [
      {
        "label": "BLACKPINK Official",
        "href": "https://www.blackpinkmusic.com/",
        "type": "official"
      }
    ]
  },
  {
    "id": "enhypen-manila-2026",
    "artist": "ENHYPEN",
    "artistSlug": "enhypen",
    "slug": "enhypen-manila-2026",
    "city": "Manila",
    "country": "Philippines",
    "venue": "Mall of Asia Arena",
    "startDate": "2026-05-16T19:00:00+08:00",
    "timezone": "Asia/Manila",
    "status": "on_sale",
    "source": "ENHYPEN official channel",
    "sourceUrl": "https://weverse.io/enhypen",
    "sourceConfidence": "official",
    "tags": [
      "Asia",
      "Arena",
      "Travel"
    ],
    "title": "ENHYPEN in Manila",
    "tourName": "ENHYPEN Tour Watch",
    "description": "ENHYPEN 的 Manila 场会把官宣入口、购票说明、场馆交通和中文观演决策放在一起。",
    "purchaseHint": "东南亚场通常要先确认支付通道和账户地区。",
    "priceNote": "不同平台的支付成功率差异很大。",
    "travelNote": "马尼拉场适合补机场到场馆的接驳建议。",
    "checklist": [
      "确认支付方式",
      "核对实名规则",
      "预留机场接驳时间"
    ],
    "heroImage": "/media/events/enhypen-manila-2026.svg",
    "ticketLinks": [
      {
        "label": "ENHYPEN Official",
        "href": "https://weverse.io/enhypen",
        "type": "official"
      }
    ]
  },
  {
    "id": "le-sserafim-hong-kong-2026",
    "artist": "LE SSERAFIM",
    "artistSlug": "le-sserafim",
    "slug": "le-sserafim-hong-kong-2026",
    "city": "Hong Kong",
    "country": "Hong Kong",
    "venue": "AsiaWorld-Arena",
    "startDate": "2026-05-24T19:00:00+08:00",
    "timezone": "Asia/Hong_Kong",
    "status": "announced",
    "source": "LE SSERAFIM official channel",
    "sourceUrl": "https://weverse.io/lesserafim",
    "sourceConfidence": "official",
    "tags": [
      "Asia",
      "Arena",
      "Local payment"
    ],
    "title": "LE SSERAFIM in Hong Kong",
    "tourName": "LE SSERAFIM Tour Watch",
    "description": "LE SSERAFIM 的 Hong Kong 场会把官宣入口、购票说明、场馆交通和中文观演决策放在一起。",
    "purchaseHint": "港区票务常涉及本地支付方式和实名规则。",
    "priceNote": "不同平台支持的支付方式差异较大。",
    "travelNote": "适合在详情页补机场快线和口岸路线。",
    "checklist": [
      "确认支付方式",
      "确认实名需求",
      "规划口岸路线"
    ],
    "heroImage": "/media/events/le-sserafim-hong-kong-2026.svg",
    "ticketLinks": [
      {
        "label": "LE SSERAFIM Official",
        "href": "https://weverse.io/lesserafim",
        "type": "official"
      }
    ]
  },
  {
    "id": "nct-dream-seoul-2026",
    "artist": "NCT DREAM",
    "artistSlug": "nct-dream",
    "slug": "nct-dream-seoul-2026",
    "city": "Seoul",
    "country": "South Korea",
    "venue": "Gocheok Sky Dome",
    "startDate": "2026-05-30T18:00:00+09:00",
    "timezone": "Asia/Seoul",
    "status": "on_sale",
    "source": "NCT DREAM official channel",
    "sourceUrl": "https://www.smtown.com/",
    "sourceConfidence": "official",
    "tags": [
      "Korea",
      "Dome",
      "Membership"
    ],
    "title": "NCT DREAM in Seoul",
    "tourName": "NCT DREAM Tour Watch",
    "description": "NCT DREAM 的 Seoul 场会把官宣入口、购票说明、场馆交通和中文观演决策放在一起。",
    "purchaseHint": "大场优先核对区块视野和安检时间。",
    "priceNote": "韩场通常对实名和取票证件要求更细。",
    "travelNote": "高尺散场后地铁会拥挤，建议留足返程缓冲。",
    "checklist": [
      "确认区块视野",
      "核对实名信息",
      "规划散场路线"
    ],
    "heroImage": "/media/events/nct-dream-seoul-2026.svg",
    "ticketLinks": [
      {
        "label": "NCT DREAM Official",
        "href": "https://www.smtown.com/",
        "type": "official"
      }
    ]
  },
  {
    "id": "ive-taipei-2026",
    "artist": "IVE",
    "artistSlug": "ive",
    "slug": "ive-taipei-2026",
    "city": "Taipei",
    "country": "Taiwan",
    "venue": "Taipei Arena",
    "startDate": "2026-06-06T19:30:00+08:00",
    "timezone": "Asia/Taipei",
    "status": "announced",
    "source": "IVE official channel",
    "sourceUrl": "https://www.ive-official.com/",
    "sourceConfidence": "official",
    "tags": [
      "Asia",
      "Arena",
      "Travel"
    ],
    "title": "IVE in Taipei",
    "tourName": "IVE Tour Watch",
    "description": "IVE 的 Taipei 场会把官宣入口、购票说明、场馆交通和中文观演决策放在一起。",
    "purchaseHint": "台北场适合先确认本地票务平台的注册和支付流程。",
    "priceNote": "留意信用卡验证和退票政策。",
    "travelNote": "台北小巨蛋周边住宿和捷运路线都比较成熟。",
    "checklist": [
      "提前注册票务平台",
      "准备可用信用卡",
      "确认捷运末班时间"
    ],
    "heroImage": "/media/events/ive-taipei-2026.svg",
    "ticketLinks": [
      {
        "label": "IVE Official",
        "href": "https://www.ive-official.com/",
        "type": "official"
      }
    ]
  },
  {
    "id": "seventeen-singapore-2026",
    "artist": "SEVENTEEN",
    "artistSlug": "seventeen",
    "slug": "seventeen-singapore-2026",
    "city": "Singapore",
    "country": "Singapore",
    "venue": "Singapore Indoor Stadium",
    "startDate": "2026-06-13T19:30:00+08:00",
    "timezone": "Asia/Singapore",
    "status": "announced",
    "source": "SEVENTEEN official channel",
    "sourceUrl": "https://weverse.io/seventeen",
    "sourceConfidence": "official",
    "tags": [
      "Asia",
      "Arena",
      "Travel"
    ],
    "title": "SEVENTEEN in Singapore",
    "tourName": "SEVENTEEN Tour Watch",
    "description": "SEVENTEEN 的 Singapore 场会把官宣入口、购票说明、场馆交通和中文观演决策放在一起。",
    "purchaseHint": "新加坡场常有主办方预售、信用卡预售和公开发售。",
    "priceNote": "跨境支付前先确认手续费和退改规则。",
    "travelNote": "酒店优先选在地铁便利区而不是景点区。",
    "checklist": [
      "关注主办方通知",
      "准备护照姓名拼写",
      "确认支付限额"
    ],
    "heroImage": "/media/events/seventeen-singapore-2026.svg",
    "ticketLinks": [
      {
        "label": "SEVENTEEN Official",
        "href": "https://weverse.io/seventeen",
        "type": "official"
      }
    ]
  },
  {
    "id": "treasure-kuala-lumpur-2026",
    "artist": "TREASURE",
    "artistSlug": "treasure",
    "slug": "treasure-kuala-lumpur-2026",
    "city": "Kuala Lumpur",
    "country": "Malaysia",
    "venue": "Axiata Arena",
    "startDate": "2026-06-20T18:00:00+08:00",
    "timezone": "Asia/Kuala_Lumpur",
    "status": "announced",
    "source": "TREASURE official channel",
    "sourceUrl": "https://www.ygfamily.com/artist/Main.asp?LANGDIV=K&ATYPE=2&ARTIDX=65",
    "sourceConfidence": "official",
    "tags": [
      "Asia",
      "Arena",
      "Travel"
    ],
    "title": "TREASURE in Kuala Lumpur",
    "tourName": "TREASURE Tour Watch",
    "description": "TREASURE 的 Kuala Lumpur 场会把官宣入口、购票说明、场馆交通和中文观演决策放在一起。",
    "purchaseHint": "马来西亚场常见多轮开票和主办方会员机制。",
    "priceNote": "先确认货币转换与支付限额。",
    "travelNote": "Bukit Jalil 一带需要提前规划散场交通。",
    "checklist": [
      "确认开票轮次",
      "检查银行卡限额",
      "规划返程路线"
    ],
    "heroImage": "/media/events/treasure-kuala-lumpur-2026.svg",
    "ticketLinks": [
      {
        "label": "TREASURE Official",
        "href": "https://www.ygfamily.com/artist/Main.asp?LANGDIV=K&ATYPE=2&ARTIDX=65",
        "type": "official"
      }
    ]
  },
  {
    "id": "btob-seoul-2026",
    "artist": "BTOB",
    "artistSlug": "btob",
    "slug": "btob-seoul-2026",
    "city": "Seoul",
    "country": "South Korea",
    "venue": "Jamsil Indoor Stadium",
    "startDate": "2026-06-21T18:00:00+09:00",
    "timezone": "Asia/Seoul",
    "status": "announced",
    "source": "BTOB official channel",
    "sourceUrl": "https://www.instagram.com/offclbtob/",
    "sourceConfidence": "official",
    "tags": [
      "Legacy",
      "Korea",
      "Seats"
    ],
    "title": "BTOB in Seoul",
    "tourName": "BTOB Tour Watch",
    "description": "BTOB 的 Seoul 场会把官宣入口、购票说明、场馆交通和中文观演决策放在一起。",
    "purchaseHint": "资深 vocal 团场次优先比较音场和正中区块。",
    "priceNote": "看台正中常比低层斜角更稳。",
    "travelNote": "蚕室一带散场人流大，返程最好提前想好。",
    "checklist": [
      "优先看正中区块",
      "确认实名信息",
      "预留返程时间"
    ],
    "heroImage": "/media/events/btob-seoul-2026.svg",
    "ticketLinks": [
      {
        "label": "BTOB Official",
        "href": "https://www.instagram.com/offclbtob/",
        "type": "official"
      }
    ]
  },
  {
    "id": "itzy-manila-2026",
    "artist": "ITZY",
    "artistSlug": "itzy",
    "slug": "itzy-manila-2026",
    "city": "Manila",
    "country": "Philippines",
    "venue": "Smart Araneta Coliseum",
    "startDate": "2026-06-27T19:00:00+08:00",
    "timezone": "Asia/Manila",
    "status": "on_sale",
    "source": "ITZY official channel",
    "sourceUrl": "https://itzy.jype.com/",
    "sourceConfidence": "official",
    "tags": [
      "Asia",
      "Arena",
      "Seats"
    ],
    "title": "ITZY in Manila",
    "tourName": "ITZY Tour Watch",
    "description": "ITZY 的 Manila 场会把官宣入口、购票说明、场馆交通和中文观演决策放在一起。",
    "purchaseHint": "先比较近舞台区域和看全景区域的取舍。",
    "priceNote": "不同票档的溢价差距较大。",
    "travelNote": "Araneta 一带交通选择多，但演出日拥堵明显。",
    "checklist": [
      "先画好选座优先级",
      "核对票档福利",
      "预留散场缓冲"
    ],
    "heroImage": "/media/events/itzy-manila-2026.svg",
    "ticketLinks": [
      {
        "label": "ITZY Official",
        "href": "https://itzy.jype.com/",
        "type": "official"
      }
    ]
  },
  {
    "id": "blackpink-paris-2026",
    "artist": "BLACKPINK",
    "artistSlug": "blackpink",
    "slug": "blackpink-paris-2026",
    "city": "Paris",
    "country": "France",
    "venue": "Accor Arena",
    "startDate": "2026-07-03T20:00:00+02:00",
    "timezone": "Europe/Paris",
    "status": "on_sale",
    "source": "BLACKPINK official channel",
    "sourceUrl": "https://www.blackpinkmusic.com/",
    "sourceConfidence": "official",
    "tags": [
      "Europe",
      "Arena",
      "VIP"
    ],
    "title": "BLACKPINK in Paris",
    "tourName": "BLACKPINK Tour Watch",
    "description": "BLACKPINK 的 Paris 场会把官宣入口、购票说明、场馆交通和中文观演决策放在一起。",
    "purchaseHint": "优先确认票务平台是否限制账户地区。",
    "priceNote": "欧元结算会带来汇率和手续费差异。",
    "travelNote": "适合补地铁末班和周边住宿策略。",
    "checklist": [
      "确认账户地区",
      "检查欧元结算卡",
      "查看 VIP 入场时间"
    ],
    "heroImage": "/media/events/blackpink-paris-2026.svg",
    "ticketLinks": [
      {
        "label": "BLACKPINK Official",
        "href": "https://www.blackpinkmusic.com/",
        "type": "official"
      }
    ]
  },
  {
    "id": "ateez-london-2026",
    "artist": "ATEEZ",
    "artistSlug": "ateez",
    "slug": "ateez-london-2026",
    "city": "London",
    "country": "United Kingdom",
    "venue": "The O2",
    "startDate": "2026-07-10T19:30:00+01:00",
    "timezone": "Europe/London",
    "status": "announced",
    "source": "ATEEZ official channel",
    "sourceUrl": "https://ateez.kqent.com/",
    "sourceConfidence": "official",
    "tags": [
      "Europe",
      "Arena",
      "Travel"
    ],
    "title": "ATEEZ in London",
    "tourName": "ATEEZ Tour Watch",
    "description": "ATEEZ 的 London 场会把官宣入口、购票说明、场馆交通和中文观演决策放在一起。",
    "purchaseHint": "英国场先看 AXS/Ticketmaster 双平台差异。",
    "priceNote": "部分福利票限制转让。",
    "travelNote": "O2 周边交通成熟，但散场排队明显。",
    "checklist": [
      "先准备两套票务账户",
      "核对福利规则",
      "留出散场时间"
    ],
    "heroImage": "/media/events/ateez-london-2026.svg",
    "ticketLinks": [
      {
        "label": "ATEEZ Official",
        "href": "https://ateez.kqent.com/",
        "type": "official"
      }
    ]
  },
  {
    "id": "xg-london-2026",
    "artist": "XG",
    "artistSlug": "xg",
    "slug": "xg-london-2026",
    "city": "London",
    "country": "United Kingdom",
    "venue": "OVO Arena Wembley",
    "startDate": "2026-07-17T19:30:00+01:00",
    "timezone": "Europe/London",
    "status": "announced",
    "source": "XG official channel",
    "sourceUrl": "https://xgalx.com/xg/",
    "sourceConfidence": "official",
    "tags": [
      "Europe",
      "Arena",
      "Travel"
    ],
    "title": "XG in London",
    "tourName": "XG Tour Watch",
    "description": "XG 的 London 场会把官宣入口、购票说明、场馆交通和中文观演决策放在一起。",
    "purchaseHint": "海外场要先确认站席和看台票差异。",
    "priceNote": "英区卡支付成功率很关键。",
    "travelNote": "伦敦场适合补夜间交通和地铁换乘建议。",
    "checklist": [
      "核对站席规则",
      "测试支付方式",
      "确认返程车次"
    ],
    "heroImage": "/media/events/xg-london-2026.svg",
    "ticketLinks": [
      {
        "label": "XG Official",
        "href": "https://xgalx.com/xg/",
        "type": "official"
      }
    ]
  },
  {
    "id": "twice-tokyo-2026",
    "artist": "TWICE",
    "artistSlug": "twice",
    "slug": "twice-tokyo-2026",
    "city": "Tokyo",
    "country": "Japan",
    "venue": "Tokyo Dome",
    "startDate": "2026-07-25T18:00:00+09:00",
    "timezone": "Asia/Tokyo",
    "status": "sold_out",
    "source": "TWICE official channel",
    "sourceUrl": "https://twice.jype.com/",
    "sourceConfidence": "official",
    "tags": [
      "Japan",
      "Dome",
      "Waitlist"
    ],
    "title": "TWICE in Tokyo",
    "tourName": "TWICE Tour Watch",
    "description": "TWICE 的 Tokyo 场会把官宣入口、购票说明、场馆交通和中文观演决策放在一起。",
    "purchaseHint": "巨蛋场要优先看抽选和官方补票。",
    "priceNote": "票档差异和场内视野差距都很大。",
    "travelNote": "东京场适合补巨蛋周边酒店与返程经验。",
    "checklist": [
      "确认抽选结果",
      "查看官方补票",
      "预订返程交通"
    ],
    "heroImage": "/media/events/twice-tokyo-2026.svg",
    "ticketLinks": [
      {
        "label": "TWICE Official",
        "href": "https://twice.jype.com/",
        "type": "official"
      }
    ]
  },
  {
    "id": "boynextdoor-seoul-2026",
    "artist": "BOYNEXTDOOR",
    "artistSlug": "boynextdoor",
    "slug": "boynextdoor-seoul-2026",
    "city": "Seoul",
    "country": "South Korea",
    "venue": "Olympic Hall",
    "startDate": "2026-08-01T18:00:00+09:00",
    "timezone": "Asia/Seoul",
    "status": "on_sale",
    "source": "BOYNEXTDOOR official channel",
    "sourceUrl": "https://weverse.io/boynextdoor",
    "sourceConfidence": "official",
    "tags": [
      "Fancon",
      "Korea",
      "Membership"
    ],
    "title": "BOYNEXTDOOR in Seoul",
    "tourName": "BOYNEXTDOOR Tour Watch",
    "description": "BOYNEXTDOOR 的 Seoul 场会把官宣入口、购票说明、场馆交通和中文观演决策放在一起。",
    "purchaseHint": "fancon 场通常更看重会员预售和福利说明。",
    "priceNote": "不同票档福利差距可能大于座位差距。",
    "travelNote": "首尔小场馆更适合补周边排队和安检提示。",
    "checklist": [
      "核对福利票规则",
      "确认会员认证",
      "留意入场队列"
    ],
    "heroImage": "/media/events/boynextdoor-seoul-2026.svg",
    "ticketLinks": [
      {
        "label": "BOYNEXTDOOR Official",
        "href": "https://weverse.io/boynextdoor",
        "type": "official"
      }
    ]
  },
  {
    "id": "tws-yokohama-2026",
    "artist": "TWS",
    "artistSlug": "tws",
    "slug": "tws-yokohama-2026",
    "city": "Yokohama",
    "country": "Japan",
    "venue": "K-Arena Yokohama",
    "startDate": "2026-08-08T18:00:00+09:00",
    "timezone": "Asia/Tokyo",
    "status": "announced",
    "source": "TWS official channel",
    "sourceUrl": "https://weverse.io/tws",
    "sourceConfidence": "official",
    "tags": [
      "Japan",
      "Arena",
      "Rookie"
    ],
    "title": "TWS in Yokohama",
    "tourName": "TWS Tour Watch",
    "description": "TWS 的 Yokohama 场会把官宣入口、购票说明、场馆交通和中文观演决策放在一起。",
    "purchaseHint": "日本新团场要重点看会员抽选和二轮抽选。",
    "priceNote": "新团演出常出现票务节奏变化。",
    "travelNote": "横滨场适合补海滨区住宿和散场路线。",
    "checklist": [
      "关注抽选节点",
      "准备日区账号",
      "规划返程路线"
    ],
    "heroImage": "/media/events/tws-yokohama-2026.svg",
    "ticketLinks": [
      {
        "label": "TWS Official",
        "href": "https://weverse.io/tws",
        "type": "official"
      }
    ]
  },
  {
    "id": "andteam-saitama-2026",
    "artist": "&TEAM",
    "artistSlug": "andteam",
    "slug": "andteam-saitama-2026",
    "city": "Saitama",
    "country": "Japan",
    "venue": "Saitama Super Arena",
    "startDate": "2026-08-15T18:00:00+09:00",
    "timezone": "Asia/Tokyo",
    "status": "on_sale",
    "source": "&TEAM official channel",
    "sourceUrl": "https://weverse.io/andteam",
    "sourceConfidence": "official",
    "tags": [
      "Japan",
      "Arena",
      "Travel"
    ],
    "title": "&TEAM in Saitama",
    "tourName": "&TEAM Tour Watch",
    "description": "&TEAM 的 Saitama 场会把官宣入口、购票说明、场馆交通和中文观演决策放在一起。",
    "purchaseHint": "SSA 场适合优先看区块视线和站席规则。",
    "priceNote": "不同区块对主舞台和延伸台视野差异很大。",
    "travelNote": "埼玉场返程列车和酒店选择要尽早确定。",
    "checklist": [
      "确认区块图",
      "核对电子票说明",
      "提前看返程列车"
    ],
    "heroImage": "/media/events/andteam-saitama-2026.svg",
    "ticketLinks": [
      {
        "label": "&TEAM Official",
        "href": "https://weverse.io/andteam",
        "type": "official"
      }
    ]
  },
  {
    "id": "zerobaseone-macau-2026",
    "artist": "ZEROBASEONE",
    "artistSlug": "zerobaseone",
    "slug": "zerobaseone-macau-2026",
    "city": "Macau",
    "country": "Macau",
    "venue": "Galaxy Arena",
    "startDate": "2026-08-22T19:00:00+08:00",
    "timezone": "Asia/Macau",
    "status": "announced",
    "source": "ZEROBASEONE official channel",
    "sourceUrl": "https://zb1-official.com/",
    "sourceConfidence": "official",
    "tags": [
      "Asia",
      "Arena",
      "Travel"
    ],
    "title": "ZEROBASEONE in Macau",
    "tourName": "ZEROBASEONE Tour Watch",
    "description": "ZEROBASEONE 的 Macau 场会把官宣入口、购票说明、场馆交通和中文观演决策放在一起。",
    "purchaseHint": "澳门场常涉及跨境住宿和口岸动线。",
    "priceNote": "先确认票务平台是否支持国际支付。",
    "travelNote": "银河综艺馆散场后叫车和口岸压力都较大。",
    "checklist": [
      "确认支付方式",
      "预留口岸时间",
      "看酒店接驳"
    ],
    "heroImage": "/media/events/zerobaseone-macau-2026.svg",
    "ticketLinks": [
      {
        "label": "ZEROBASEONE Official",
        "href": "https://zb1-official.com/",
        "type": "official"
      }
    ]
  },
  {
    "id": "riize-hong-kong-2026",
    "artist": "RIIZE",
    "artistSlug": "riize",
    "slug": "riize-hong-kong-2026",
    "city": "Hong Kong",
    "country": "Hong Kong",
    "venue": "AsiaWorld-Arena",
    "startDate": "2026-08-29T19:00:00+08:00",
    "timezone": "Asia/Hong_Kong",
    "status": "announced",
    "source": "RIIZE official channel",
    "sourceUrl": "https://www.smtown.com/",
    "sourceConfidence": "official",
    "tags": [
      "Asia",
      "Arena",
      "Travel"
    ],
    "title": "RIIZE in Hong Kong",
    "tourName": "RIIZE Tour Watch",
    "description": "RIIZE 的 Hong Kong 场会把官宣入口、购票说明、场馆交通和中文观演决策放在一起。",
    "purchaseHint": "适合补充港区购票、实名和场馆动线。",
    "priceNote": "同一场次不同平台的余票节奏会不一样。",
    "travelNote": "机场快线和的士预算都要提前算。",
    "checklist": [
      "确认平台规则",
      "核对实名信息",
      "预留交通预算"
    ],
    "heroImage": "/media/events/riize-hong-kong-2026.svg",
    "ticketLinks": [
      {
        "label": "RIIZE Official",
        "href": "https://www.smtown.com/",
        "type": "official"
      }
    ]
  },
  {
    "id": "h1-key-seoul-2026",
    "artist": "H1-KEY",
    "artistSlug": "h1-key",
    "slug": "h1-key-seoul-2026",
    "city": "Seoul",
    "country": "South Korea",
    "venue": "MUV Hall",
    "startDate": "2026-08-30T18:00:00+09:00",
    "timezone": "Asia/Seoul",
    "status": "announced",
    "source": "H1-KEY official channel",
    "sourceUrl": "https://www.instagram.com/h1key_official/",
    "sourceConfidence": "official",
    "tags": [
      "Korea",
      "Theater",
      "Rookie"
    ],
    "title": "H1-KEY in Seoul",
    "tourName": "H1-KEY Tour Watch",
    "description": "H1-KEY 的 Seoul 场会把官宣入口、购票说明、场馆交通和中文观演决策放在一起。",
    "purchaseHint": "中小型场馆更看视角和队列。",
    "priceNote": "福利票说明比票档名字更重要。",
    "travelNote": "江南区域散场打车成本要先估。",
    "checklist": [
      "确认福利",
      "提前排队",
      "估算打车"
    ],
    "heroImage": "/media/events/h1-key-seoul-2026.svg",
    "ticketLinks": [
      {
        "label": "H1-KEY Official",
        "href": "https://www.instagram.com/h1key_official/",
        "type": "official"
      }
    ]
  },
  {
    "id": "jin-osaka-2026",
    "artist": "Jin",
    "artistSlug": "jin",
    "slug": "jin-osaka-2026",
    "city": "Osaka",
    "country": "Japan",
    "venue": "Osaka-jō Hall",
    "startDate": "2026-09-05T18:00:00+09:00",
    "timezone": "Asia/Tokyo",
    "status": "announced",
    "source": "Jin official channel",
    "sourceUrl": "https://weverse.io/jin",
    "sourceConfidence": "official",
    "tags": [
      "Solo",
      "Japan",
      "Membership"
    ],
    "title": "Jin in Osaka",
    "tourName": "Jin Tour Watch",
    "description": "Jin 的 Osaka 场会把官宣入口、购票说明、场馆交通和中文观演决策放在一起。",
    "purchaseHint": "solo 日本场优先看抽选和会员。",
    "priceNote": "电子票和入场证件细节不能漏。",
    "travelNote": "大阪市区返程路线提早锁定。",
    "checklist": [
      "确认抽选",
      "核对电子票",
      "规划返程"
    ],
    "heroImage": "/media/events/jin-osaka-2026.svg",
    "ticketLinks": [
      {
        "label": "Jin Official",
        "href": "https://weverse.io/jin",
        "type": "official"
      }
    ]
  },
  {
    "id": "katseye-new-york-2026",
    "artist": "KATSEYE",
    "artistSlug": "katseye",
    "slug": "katseye-new-york-2026",
    "city": "New York",
    "country": "United States",
    "venue": "Hammerstein Ballroom",
    "startDate": "2026-09-05T20:00:00-04:00",
    "timezone": "America/Los_Angeles",
    "status": "announced",
    "source": "KATSEYE official channel",
    "sourceUrl": "https://weverse.io/katseye",
    "sourceConfidence": "official",
    "tags": [
      "Showcase",
      "North America",
      "GA"
    ],
    "title": "KATSEYE in New York",
    "tourName": "KATSEYE Tour Watch",
    "description": "KATSEYE 的 New York 场会把官宣入口、购票说明、场馆交通和中文观演决策放在一起。",
    "purchaseHint": "GA standing 场优先看排队和包袋政策。",
    "priceNote": "北美小场抢位比单纯票档更重要。",
    "travelNote": "纽约场适合补地铁、安检和排队建议。",
    "checklist": [
      "查看包袋政策",
      "确认排队时间",
      "规划夜间返程"
    ],
    "heroImage": "/media/events/katseye-new-york-2026.svg",
    "ticketLinks": [
      {
        "label": "KATSEYE Official",
        "href": "https://weverse.io/katseye",
        "type": "official"
      }
    ]
  },
  {
    "id": "evnne-seoul-2026",
    "artist": "EVNNE",
    "artistSlug": "evnne",
    "slug": "evnne-seoul-2026",
    "city": "Seoul",
    "country": "South Korea",
    "venue": "Olympic Hall",
    "startDate": "2026-09-06T18:00:00+09:00",
    "timezone": "Asia/Seoul",
    "status": "announced",
    "source": "EVNNE official channel",
    "sourceUrl": "https://www.instagram.com/evnne_official/",
    "sourceConfidence": "official",
    "tags": [
      "Fancon",
      "Korea",
      "Membership"
    ],
    "title": "EVNNE in Seoul",
    "tourName": "EVNNE Tour Watch",
    "description": "EVNNE 的 Seoul 场会把官宣入口、购票说明、场馆交通和中文观演决策放在一起。",
    "purchaseHint": "fancon 场更要看福利票和会员入口。",
    "priceNote": "福利差异可能大于座位差异。",
    "travelNote": "小场馆排队节奏快，提早到场更稳。",
    "checklist": [
      "确认会员入口",
      "核对福利说明",
      "提前到场"
    ],
    "heroImage": "/media/events/evnne-seoul-2026.svg",
    "ticketLinks": [
      {
        "label": "EVNNE Official",
        "href": "https://www.instagram.com/evnne_official/",
        "type": "official"
      }
    ]
  },
  {
    "id": "babymonster-jakarta-2026",
    "artist": "BABYMONSTER",
    "artistSlug": "babymonster",
    "slug": "babymonster-jakarta-2026",
    "city": "Jakarta",
    "country": "Indonesia",
    "venue": "ICE BSD Hall 5",
    "startDate": "2026-09-12T19:00:00+07:00",
    "timezone": "Asia/Jakarta",
    "status": "announced",
    "source": "BABYMONSTER official channel",
    "sourceUrl": "https://www.ygfamily.com/artist/Main.asp?LANGDIV=K&ATYPE=2&ARTIDX=70",
    "sourceConfidence": "official",
    "tags": [
      "Asia",
      "Arena",
      "Travel"
    ],
    "title": "BABYMONSTER in Jakarta",
    "tourName": "BABYMONSTER Tour Watch",
    "description": "BABYMONSTER 的 Jakarta 场会把官宣入口、购票说明、场馆交通和中文观演决策放在一起。",
    "purchaseHint": "雅加达场适合补支付、口岸和交通信息。",
    "priceNote": "部分主办方会分平台和分轮开票。",
    "travelNote": "BSD 演出日路面交通时间不可低估。",
    "checklist": [
      "准备支付卡",
      "确认平台账号",
      "预留出城时间"
    ],
    "heroImage": "/media/events/babymonster-jakarta-2026.svg",
    "ticketLinks": [
      {
        "label": "BABYMONSTER Official",
        "href": "https://www.ygfamily.com/artist/Main.asp?LANGDIV=K&ATYPE=2&ARTIDX=70",
        "type": "official"
      }
    ]
  },
  {
    "id": "taemin-bangkok-2026",
    "artist": "Taemin",
    "artistSlug": "taemin",
    "slug": "taemin-bangkok-2026",
    "city": "Bangkok",
    "country": "Thailand",
    "venue": "Impact Exhibition Hall 5",
    "startDate": "2026-09-12T19:00:00+07:00",
    "timezone": "Asia/Bangkok",
    "status": "announced",
    "source": "Taemin official channel",
    "sourceUrl": "https://www.smtown.com/",
    "sourceConfidence": "official",
    "tags": [
      "Solo",
      "Asia",
      "Performance"
    ],
    "title": "Taemin in Bangkok",
    "tourName": "Taemin Tour Watch",
    "description": "Taemin 的 Bangkok 场会把官宣入口、购票说明、场馆交通和中文观演决策放在一起。",
    "purchaseHint": "表演型 solo 更值得看舞台延伸和视角。",
    "priceNote": "站位和屏幕位置一起考虑。",
    "travelNote": "曼谷返程提早锁定。",
    "checklist": [
      "比较视角",
      "确认站位",
      "预订返程"
    ],
    "heroImage": "/media/events/taemin-bangkok-2026.svg",
    "ticketLinks": [
      {
        "label": "Taemin Official",
        "href": "https://www.smtown.com/",
        "type": "official"
      }
    ]
  },
  {
    "id": "stayc-seoul-2026",
    "artist": "STAYC",
    "artistSlug": "stayc",
    "slug": "stayc-seoul-2026",
    "city": "Seoul",
    "country": "South Korea",
    "venue": "Handball Gymnasium",
    "startDate": "2026-09-13T18:00:00+09:00",
    "timezone": "Asia/Seoul",
    "status": "announced",
    "source": "STAYC official channel",
    "sourceUrl": "https://www.instagram.com/stayc_highup/",
    "sourceConfidence": "official",
    "tags": [
      "Korea",
      "Arena",
      "Travel"
    ],
    "title": "STAYC in Seoul",
    "tourName": "STAYC Tour Watch",
    "description": "STAYC 的 Seoul 场会把官宣入口、购票说明、场馆交通和中文观演决策放在一起。",
    "purchaseHint": "手球馆更需要提早看区块图。",
    "priceNote": "近舞台不一定更适合看全景。",
    "travelNote": "园区演出日人流固定偏大。",
    "checklist": [
      "确认区块图",
      "比较近区和中区",
      "预留返程"
    ],
    "heroImage": "/media/events/stayc-seoul-2026.svg",
    "ticketLinks": [
      {
        "label": "STAYC Official",
        "href": "https://www.instagram.com/stayc_highup/",
        "type": "official"
      }
    ]
  },
  {
    "id": "fromis-9-seoul-2026",
    "artist": "fromis_9",
    "artistSlug": "fromis-9",
    "slug": "fromis-9-seoul-2026",
    "city": "Seoul",
    "country": "South Korea",
    "venue": "Olympic Hall",
    "startDate": "2026-09-14T18:00:00+09:00",
    "timezone": "Asia/Seoul",
    "status": "announced",
    "source": "fromis_9 official channel",
    "sourceUrl": "https://weverse.io/fromis9",
    "sourceConfidence": "official",
    "tags": [
      "Korea",
      "Live",
      "Fandom"
    ],
    "title": "fromis_9 in Seoul",
    "tourName": "fromis_9 Tour Watch",
    "description": "fromis_9 的 Seoul 场会把官宣入口、购票说明、场馆交通和中文观演决策放在一起。",
    "purchaseHint": "核心饭观演更适合关注官宣和队列。",
    "priceNote": "福利和场馆动线值得单独整理。",
    "travelNote": "园区演出日提前到场更稳。",
    "checklist": [
      "盯官宣",
      "看福利",
      "提早到场"
    ],
    "heroImage": "/media/events/fromis-9-seoul-2026.svg",
    "ticketLinks": [
      {
        "label": "fromis_9 Official",
        "href": "https://weverse.io/fromis9",
        "type": "official"
      }
    ]
  },
  {
    "id": "stray-kids-bangkok-2026",
    "artist": "Stray Kids",
    "artistSlug": "stray-kids",
    "slug": "stray-kids-bangkok-2026",
    "city": "Bangkok",
    "country": "Thailand",
    "venue": "Impact Arena",
    "startDate": "2026-09-19T19:00:00+07:00",
    "timezone": "Asia/Bangkok",
    "status": "on_sale",
    "source": "Stray Kids official channel",
    "sourceUrl": "https://www.straykids.jype.com/",
    "sourceConfidence": "official",
    "tags": [
      "Asia",
      "Arena",
      "Travel"
    ],
    "title": "Stray Kids in Bangkok",
    "tourName": "Stray Kids Tour Watch",
    "description": "Stray Kids 的 Bangkok 场会把官宣入口、购票说明、场馆交通和中文观演决策放在一起。",
    "purchaseHint": "泰国场要优先确认支付方式、票务区和站席规则。",
    "priceNote": "高需求场次容易出现抢票拥堵。",
    "travelNote": "IMPACT 周边住宿和返程策略要提早做。",
    "checklist": [
      "准备多张支付卡",
      "确认站席规则",
      "订好场馆周边酒店"
    ],
    "heroImage": "/media/events/stray-kids-bangkok-2026.svg",
    "ticketLinks": [
      {
        "label": "Stray Kids Official",
        "href": "https://www.straykids.jype.com/",
        "type": "official"
      }
    ]
  },
  {
    "id": "woodz-seoul-2026",
    "artist": "WOODZ",
    "artistSlug": "woodz",
    "slug": "woodz-seoul-2026",
    "city": "Seoul",
    "country": "South Korea",
    "venue": "YES24 Live Hall",
    "startDate": "2026-09-20T18:00:00+09:00",
    "timezone": "Asia/Seoul",
    "status": "announced",
    "source": "WOODZ official channel",
    "sourceUrl": "https://www.instagram.com/woodz_dnwm/",
    "sourceConfidence": "official",
    "tags": [
      "Solo",
      "Korea",
      "Theater"
    ],
    "title": "WOODZ in Seoul",
    "tourName": "WOODZ Tour Watch",
    "description": "WOODZ 的 Seoul 场会把官宣入口、购票说明、场馆交通和中文观演决策放在一起。",
    "purchaseHint": "solo 场更值得看视角和音场。",
    "priceNote": "站席与坐席体验差异很大。",
    "travelNote": "广津区返程地铁更稳。",
    "checklist": [
      "确认站席规则",
      "看好区块",
      "提早到场"
    ],
    "heroImage": "/media/events/woodz-seoul-2026.svg",
    "ticketLinks": [
      {
        "label": "WOODZ Official",
        "href": "https://www.instagram.com/woodz_dnwm/",
        "type": "official"
      }
    ]
  },
  {
    "id": "iu-taipei-2026",
    "artist": "IU",
    "artistSlug": "iu",
    "slug": "iu-taipei-2026",
    "city": "Taipei",
    "country": "Taiwan",
    "venue": "Taipei Arena",
    "startDate": "2026-09-26T19:30:00+08:00",
    "timezone": "Asia/Taipei",
    "status": "announced",
    "source": "IU official channel",
    "sourceUrl": "https://www.iu-official.com/",
    "sourceConfidence": "official",
    "tags": [
      "Solo",
      "Arena",
      "Seats"
    ],
    "title": "IU in Taipei",
    "tourName": "IU Tour Watch",
    "description": "IU 的 Taipei 场会把官宣入口、购票说明、场馆交通和中文观演决策放在一起。",
    "purchaseHint": "solo 场更值得花时间比较区块和视角。",
    "priceNote": "不同票档的观感差异可能大于价差。",
    "travelNote": "台北小巨蛋散场交通稳定，但末班时间仍要确认。",
    "checklist": [
      "先看区块视角",
      "比较票档价格",
      "确认捷运末班"
    ],
    "heroImage": "/media/events/iu-taipei-2026.svg",
    "ticketLinks": [
      {
        "label": "IU Official",
        "href": "https://www.iu-official.com/",
        "type": "official"
      }
    ]
  },
  {
    "id": "nexz-osaka-2026",
    "artist": "NEXZ",
    "artistSlug": "nexz",
    "slug": "nexz-osaka-2026",
    "city": "Osaka",
    "country": "Japan",
    "venue": "Asue Arena Osaka",
    "startDate": "2026-09-27T18:00:00+09:00",
    "timezone": "Asia/Tokyo",
    "status": "announced",
    "source": "NEXZ official channel",
    "sourceUrl": "https://nexz-official.com/",
    "sourceConfidence": "official",
    "tags": [
      "Japan",
      "Arena",
      "Travel"
    ],
    "title": "NEXZ in Osaka",
    "tourName": "NEXZ Tour Watch",
    "description": "NEXZ 的 Osaka 场会把官宣入口、购票说明、场馆交通和中文观演决策放在一起。",
    "purchaseHint": "日本路线要优先看账号和抽选。",
    "priceNote": "先准备支付方式和取票方式。",
    "travelNote": "大阪返程列车要提前确认。",
    "checklist": [
      "准备日区账号",
      "确认取票方式",
      "预留返程"
    ],
    "heroImage": "/media/events/nexz-osaka-2026.svg",
    "ticketLinks": [
      {
        "label": "NEXZ Official",
        "href": "https://nexz-official.com/",
        "type": "official"
      }
    ]
  },
  {
    "id": "twice-singapore-2026",
    "artist": "TWICE",
    "artistSlug": "twice",
    "slug": "twice-singapore-2026",
    "city": "Singapore",
    "country": "Singapore",
    "venue": "National Stadium",
    "startDate": "2026-10-03T19:30:00+08:00",
    "timezone": "Asia/Singapore",
    "status": "announced",
    "source": "TWICE official channel",
    "sourceUrl": "https://twice.jype.com/",
    "sourceConfidence": "official",
    "tags": [
      "Asia",
      "Stadium",
      "Travel"
    ],
    "title": "TWICE in Singapore",
    "tourName": "TWICE Tour Watch",
    "description": "TWICE 的 Singapore 场会把官宣入口、购票说明、场馆交通和中文观演决策放在一起。",
    "purchaseHint": "新加坡大场要先看平台预售和看台视野。",
    "priceNote": "体育场票档跨度很大。",
    "travelNote": "国家体育场演出日散场人流密集。",
    "checklist": [
      "核对预售规则",
      "比较视野图",
      "规划散场交通"
    ],
    "heroImage": "/media/events/twice-singapore-2026.svg",
    "ticketLinks": [
      {
        "label": "TWICE Official",
        "href": "https://twice.jype.com/",
        "type": "official"
      }
    ]
  },
  {
    "id": "qwer-seoul-2026",
    "artist": "QWER",
    "artistSlug": "qwer",
    "slug": "qwer-seoul-2026",
    "city": "Seoul",
    "country": "South Korea",
    "venue": "Olympic Hall",
    "startDate": "2026-10-04T18:00:00+09:00",
    "timezone": "Asia/Seoul",
    "status": "on_sale",
    "source": "QWER official channel",
    "sourceUrl": "https://www.instagram.com/qwerband_official/",
    "sourceConfidence": "official",
    "tags": [
      "Band",
      "Korea",
      "Theater"
    ],
    "title": "QWER in Seoul",
    "tourName": "QWER Tour Watch",
    "description": "QWER 的 Seoul 场会把官宣入口、购票说明、场馆交通和中文观演决策放在一起。",
    "purchaseHint": "乐队场更值得看音场和视线。",
    "priceNote": "正中看台常比侧面更稳。",
    "travelNote": "奥林匹克公园区域散场节奏固定。",
    "checklist": [
      "优先看音场",
      "选正中区",
      "提早返程"
    ],
    "heroImage": "/media/events/qwer-seoul-2026.svg",
    "ticketLinks": [
      {
        "label": "QWER Official",
        "href": "https://www.instagram.com/qwerband_official/",
        "type": "official"
      }
    ]
  },
  {
    "id": "nmixx-seoul-2026",
    "artist": "NMIXX",
    "artistSlug": "nmixx",
    "slug": "nmixx-seoul-2026",
    "city": "Seoul",
    "country": "South Korea",
    "venue": "Blue Square Mastercard Hall",
    "startDate": "2026-10-10T18:00:00+09:00",
    "timezone": "Asia/Seoul",
    "status": "announced",
    "source": "NMIXX official channel",
    "sourceUrl": "https://nmixx.jype.com/",
    "sourceConfidence": "official",
    "tags": [
      "Korea",
      "Theater",
      "Close-up"
    ],
    "title": "NMIXX in Seoul",
    "tourName": "NMIXX Tour Watch",
    "description": "NMIXX 的 Seoul 场会把官宣入口、购票说明、场馆交通和中文观演决策放在一起。",
    "purchaseHint": "剧场型场馆更值得细看楼层和视角。",
    "priceNote": "小场和中场的体验差距明显。",
    "travelNote": "首尔剧场场通常安检和队列节奏更快。",
    "checklist": [
      "核对楼层座位",
      "留意包袋规则",
      "提早到场"
    ],
    "heroImage": "/media/events/nmixx-seoul-2026.svg",
    "ticketLinks": [
      {
        "label": "NMIXX Official",
        "href": "https://nmixx.jype.com/",
        "type": "official"
      }
    ]
  },
  {
    "id": "kep1er-yokohama-2026",
    "artist": "Kep1er",
    "artistSlug": "kep1er",
    "slug": "kep1er-yokohama-2026",
    "city": "Yokohama",
    "country": "Japan",
    "venue": "K-Arena Yokohama",
    "startDate": "2026-10-11T18:00:00+09:00",
    "timezone": "Asia/Tokyo",
    "status": "announced",
    "source": "Kep1er official channel",
    "sourceUrl": "https://www.instagram.com/official.kep1er/",
    "sourceConfidence": "official",
    "tags": [
      "Japan",
      "Arena",
      "Travel"
    ],
    "title": "Kep1er in Yokohama",
    "tourName": "Kep1er Tour Watch",
    "description": "Kep1er 的 Yokohama 场会把官宣入口、购票说明、场馆交通和中文观演决策放在一起。",
    "purchaseHint": "日本场优先看抽选和电子票。",
    "priceNote": "二轮抽选往往也有机会。",
    "travelNote": "横滨返程和住宿可一起规划。",
    "checklist": [
      "确认抽选轮次",
      "核对电子票",
      "规划返程"
    ],
    "heroImage": "/media/events/kep1er-yokohama-2026.svg",
    "ticketLinks": [
      {
        "label": "Kep1er Official",
        "href": "https://www.instagram.com/official.kep1er/",
        "type": "official"
      }
    ]
  },
  {
    "id": "illit-seoul-2026",
    "artist": "ILLIT",
    "artistSlug": "illit",
    "slug": "illit-seoul-2026",
    "city": "Seoul",
    "country": "South Korea",
    "venue": "Olympic Hall",
    "startDate": "2026-10-12T18:00:00+09:00",
    "timezone": "Asia/Seoul",
    "status": "announced",
    "source": "ILLIT official channel",
    "sourceUrl": "https://weverse.io/illit",
    "sourceConfidence": "official",
    "tags": [
      "Rookie",
      "Korea",
      "Membership"
    ],
    "title": "ILLIT in Seoul",
    "tourName": "ILLIT Tour Watch",
    "description": "ILLIT 的 Seoul 场会把官宣入口、购票说明、场馆交通和中文观演决策放在一起。",
    "purchaseHint": "新团首尔场优先看会员路径。",
    "priceNote": "福利差异要比票档名字更重要。",
    "travelNote": "排队和队列节奏值得提前看。",
    "checklist": [
      "确认会员入口",
      "核对福利",
      "提前到场"
    ],
    "heroImage": "/media/events/illit-seoul-2026.svg",
    "ticketLinks": [
      {
        "label": "ILLIT Official",
        "href": "https://weverse.io/illit",
        "type": "official"
      }
    ]
  },
  {
    "id": "taeyeon-seoul-2026",
    "artist": "Taeyeon",
    "artistSlug": "taeyeon",
    "slug": "taeyeon-seoul-2026",
    "city": "Seoul",
    "country": "South Korea",
    "venue": "KSPO Dome",
    "startDate": "2026-10-17T18:00:00+09:00",
    "timezone": "Asia/Seoul",
    "status": "announced",
    "source": "Taeyeon official channel",
    "sourceUrl": "https://www.smtown.com/",
    "sourceConfidence": "official",
    "tags": [
      "Solo",
      "Korea",
      "Seats"
    ],
    "title": "Taeyeon in Seoul",
    "tourName": "Taeyeon Tour Watch",
    "description": "Taeyeon 的 Seoul 场会把官宣入口、购票说明、场馆交通和中文观演决策放在一起。",
    "purchaseHint": "声场和视线通常比靠前距离更重要。",
    "priceNote": "适合优先比较中前区与高层正中的取舍。",
    "travelNote": "奥林匹克公园一带住宿和返程都要早订。",
    "checklist": [
      "优先看音场评价",
      "比较正中区块",
      "尽早订酒店"
    ],
    "heroImage": "/media/events/taeyeon-seoul-2026.svg",
    "ticketLinks": [
      {
        "label": "Taeyeon Official",
        "href": "https://www.smtown.com/",
        "type": "official"
      }
    ]
  },
  {
    "id": "wayv-macau-2026",
    "artist": "WayV",
    "artistSlug": "wayv",
    "slug": "wayv-macau-2026",
    "city": "Macau",
    "country": "Macau",
    "venue": "Broadway Theatre",
    "startDate": "2026-10-17T19:00:00+08:00",
    "timezone": "Asia/Macau",
    "status": "announced",
    "source": "WayV official channel",
    "sourceUrl": "https://www.smtown.com/",
    "sourceConfidence": "official",
    "tags": [
      "Macau",
      "Travel",
      "Arena"
    ],
    "title": "WayV in Macau",
    "tourName": "WayV Tour Watch",
    "description": "WayV 的 Macau 场会把官宣入口、购票说明、场馆交通和中文观演决策放在一起。",
    "purchaseHint": "澳门场要优先看口岸和酒店接驳。",
    "priceNote": "平台支付和实名要先确认。",
    "travelNote": "返程时间缓冲要给足。",
    "checklist": [
      "确认支付",
      "预留口岸时间",
      "看接驳"
    ],
    "heroImage": "/media/events/wayv-macau-2026.svg",
    "ticketLinks": [
      {
        "label": "WayV Official",
        "href": "https://www.smtown.com/",
        "type": "official"
      }
    ]
  },
  {
    "id": "shinee-tokyo-2026",
    "artist": "SHINee",
    "artistSlug": "shinee",
    "slug": "shinee-tokyo-2026",
    "city": "Tokyo",
    "country": "Japan",
    "venue": "Yoyogi National Stadium First Gymnasium",
    "startDate": "2026-10-18T18:00:00+09:00",
    "timezone": "Asia/Tokyo",
    "status": "announced",
    "source": "SHINee official channel",
    "sourceUrl": "https://www.smtown.com/",
    "sourceConfidence": "official",
    "tags": [
      "Japan",
      "Legacy",
      "Arena"
    ],
    "title": "SHINee in Tokyo",
    "tourName": "SHINee Tour Watch",
    "description": "SHINee 的 Tokyo 场会把官宣入口、购票说明、场馆交通和中文观演决策放在一起。",
    "purchaseHint": "日本资深团场优先看抽选和补票。",
    "priceNote": "高需求时补票也值得等待。",
    "travelNote": "代代木区域返程成熟，但演出日会拥挤。",
    "checklist": [
      "确认抽选",
      "等补票",
      "规划返程"
    ],
    "heroImage": "/media/events/shinee-tokyo-2026.svg",
    "ticketLinks": [
      {
        "label": "SHINee Official",
        "href": "https://www.smtown.com/",
        "type": "official"
      }
    ]
  },
  {
    "id": "p1harmony-newark-2026",
    "artist": "P1Harmony",
    "artistSlug": "p1harmony",
    "slug": "p1harmony-newark-2026",
    "city": "Newark",
    "country": "United States",
    "venue": "Prudential Center",
    "startDate": "2026-10-18T20:00:00-04:00",
    "timezone": "America/New_York",
    "status": "announced",
    "source": "P1Harmony official channel",
    "sourceUrl": "https://p1harmony.us/",
    "sourceConfidence": "official",
    "tags": [
      "North America",
      "Arena",
      "Travel"
    ],
    "title": "P1Harmony in Newark",
    "tourName": "P1Harmony Tour Watch",
    "description": "P1Harmony 的 Newark 场会把官宣入口、购票说明、场馆交通和中文观演决策放在一起。",
    "purchaseHint": "北美场优先看 presale 和停车。",
    "priceNote": "下层看台与 floor 的性价比差异很大。",
    "travelNote": "纽瓦克返程和酒店区位要提前确认。",
    "checklist": [
      "确认 presale",
      "比较区块",
      "确认返程"
    ],
    "heroImage": "/media/events/p1harmony-newark-2026.svg",
    "ticketLinks": [
      {
        "label": "P1Harmony Official",
        "href": "https://p1harmony.us/",
        "type": "official"
      }
    ]
  },
  {
    "id": "treasure-bangkok-2026",
    "artist": "TREASURE",
    "artistSlug": "treasure",
    "slug": "treasure-bangkok-2026",
    "city": "Bangkok",
    "country": "Thailand",
    "venue": "Impact Arena",
    "startDate": "2026-10-24T19:00:00+07:00",
    "timezone": "Asia/Bangkok",
    "status": "announced",
    "source": "TREASURE official channel",
    "sourceUrl": "https://www.ygfamily.com/artist/Main.asp?LANGDIV=K&ATYPE=2&ARTIDX=65",
    "sourceConfidence": "official",
    "tags": [
      "Asia",
      "Arena",
      "Travel"
    ],
    "title": "TREASURE in Bangkok",
    "tourName": "TREASURE Tour Watch",
    "description": "TREASURE 的 Bangkok 场会把官宣入口、购票说明、场馆交通和中文观演决策放在一起。",
    "purchaseHint": "适合补泰国场多轮售票和站席经验。",
    "priceNote": "不同票档福利差异较大。",
    "travelNote": "IMPACT 返程和住宿建议值得单独写清楚。",
    "checklist": [
      "确认开票轮次",
      "看福利差异",
      "规划返程"
    ],
    "heroImage": "/media/events/treasure-bangkok-2026.svg",
    "ticketLinks": [
      {
        "label": "TREASURE Official",
        "href": "https://www.ygfamily.com/artist/Main.asp?LANGDIV=K&ATYPE=2&ARTIDX=65",
        "type": "official"
      }
    ]
  },
  {
    "id": "triples-taipei-2026",
    "artist": "tripleS",
    "artistSlug": "triples",
    "slug": "triples-taipei-2026",
    "city": "Taipei",
    "country": "Taiwan",
    "venue": "TICC",
    "startDate": "2026-10-25T19:30:00+08:00",
    "timezone": "Asia/Taipei",
    "status": "announced",
    "source": "tripleS official channel",
    "sourceUrl": "https://www.mod-haus.com/",
    "sourceConfidence": "official",
    "tags": [
      "Showcase",
      "Taiwan",
      "Travel"
    ],
    "title": "tripleS in Taipei",
    "tourName": "tripleS Tour Watch",
    "description": "tripleS 的 Taipei 场会把官宣入口、购票说明、场馆交通和中文观演决策放在一起。",
    "purchaseHint": "多人结构艺人更适合先看舞台覆盖和屏幕。",
    "priceNote": "剧院型场馆更看正面视角。",
    "travelNote": "信义区返程方便，但仍要确认末班。",
    "checklist": [
      "优先正面区",
      "确认入场时间",
      "规划返程"
    ],
    "heroImage": "/media/events/triples-taipei-2026.svg",
    "ticketLinks": [
      {
        "label": "tripleS Official",
        "href": "https://www.mod-haus.com/",
        "type": "official"
      }
    ]
  },
  {
    "id": "kiss-of-life-bangkok-2026",
    "artist": "KISS OF LIFE",
    "artistSlug": "kiss-of-life",
    "slug": "kiss-of-life-bangkok-2026",
    "city": "Bangkok",
    "country": "Thailand",
    "venue": "Thunder Dome",
    "startDate": "2026-10-26T19:00:00+07:00",
    "timezone": "Asia/Bangkok",
    "status": "announced",
    "source": "KISS OF LIFE official channel",
    "sourceUrl": "https://www.s2ent.co.kr/",
    "sourceConfidence": "official",
    "tags": [
      "Asia",
      "Travel",
      "Arena"
    ],
    "title": "KISS OF LIFE in Bangkok",
    "tourName": "KISS OF LIFE Tour Watch",
    "description": "KISS OF LIFE 的 Bangkok 场会把官宣入口、购票说明、场馆交通和中文观演决策放在一起。",
    "purchaseHint": "曼谷场更看支付和交通。",
    "priceNote": "站席和坐席规则要先确认。",
    "travelNote": "散场交通最好提前锁定。",
    "checklist": [
      "确认支付",
      "看站席规则",
      "预订返程"
    ],
    "heroImage": "/media/events/kiss-of-life-bangkok-2026.svg",
    "ticketLinks": [
      {
        "label": "KISS OF LIFE Official",
        "href": "https://www.s2ent.co.kr/",
        "type": "official"
      }
    ]
  },
  {
    "id": "izna-seoul-2026",
    "artist": "izna",
    "artistSlug": "izna",
    "slug": "izna-seoul-2026",
    "city": "Seoul",
    "country": "South Korea",
    "venue": "Blue Square Mastercard Hall",
    "startDate": "2026-10-31T18:00:00+09:00",
    "timezone": "Asia/Seoul",
    "status": "announced",
    "source": "izna official channel",
    "sourceUrl": "https://www.instagram.com/izna_official/",
    "sourceConfidence": "official",
    "tags": [
      "Rookie",
      "Theater",
      "Watchlist"
    ],
    "title": "izna in Seoul",
    "tourName": "izna Tour Watch",
    "description": "izna 的 Seoul 场会把官宣入口、购票说明、场馆交通和中文观演决策放在一起。",
    "purchaseHint": "新团小中场更适合先看入场和福利。",
    "priceNote": "不同票档的近距离体验差别大。",
    "travelNote": "蓝色广场场次更适合提早到场。",
    "checklist": [
      "看福利票规则",
      "提早排队",
      "确认楼层"
    ],
    "heroImage": "/media/events/izna-seoul-2026.svg",
    "ticketLinks": [
      {
        "label": "izna Official",
        "href": "https://www.instagram.com/izna_official/",
        "type": "official"
      }
    ]
  },
  {
    "id": "jimin-singapore-2026",
    "artist": "Jimin",
    "artistSlug": "jimin",
    "slug": "jimin-singapore-2026",
    "city": "Singapore",
    "country": "Singapore",
    "venue": "Singapore Indoor Stadium",
    "startDate": "2026-11-01T19:30:00+08:00",
    "timezone": "Asia/Singapore",
    "status": "announced",
    "source": "Jimin official channel",
    "sourceUrl": "https://weverse.io/jimin",
    "sourceConfidence": "official",
    "tags": [
      "Solo",
      "Asia",
      "Travel"
    ],
    "title": "Jimin in Singapore",
    "tourName": "Jimin Tour Watch",
    "description": "Jimin 的 Singapore 场会把官宣入口、购票说明、场馆交通和中文观演决策放在一起。",
    "purchaseHint": "新加坡场要先看支付和公开发售。",
    "priceNote": "不同平台支持的卡不同。",
    "travelNote": "酒店优先沿地铁线。",
    "checklist": [
      "确认支付方式",
      "留意公开发售",
      "订好酒店"
    ],
    "heroImage": "/media/events/jimin-singapore-2026.svg",
    "ticketLinks": [
      {
        "label": "Jimin Official",
        "href": "https://weverse.io/jimin",
        "type": "official"
      }
    ]
  },
  {
    "id": "ateez-mexico-city-2026",
    "artist": "ATEEZ",
    "artistSlug": "ateez",
    "slug": "ateez-mexico-city-2026",
    "city": "Mexico City",
    "country": "Mexico",
    "venue": "Palacio de los Deportes",
    "startDate": "2026-11-01T20:00:00-06:00",
    "timezone": "America/Mexico_City",
    "status": "announced",
    "source": "ATEEZ official channel",
    "sourceUrl": "https://ateez.kqent.com/",
    "sourceConfidence": "official",
    "tags": [
      "North America",
      "Arena",
      "Travel"
    ],
    "title": "ATEEZ in Mexico City",
    "tourName": "ATEEZ Tour Watch",
    "description": "ATEEZ 的 Mexico City 场会把官宣入口、购票说明、场馆交通和中文观演决策放在一起。",
    "purchaseHint": "拉美场优先确认平台规则和支付渠道。",
    "priceNote": "跨区购票更要留意结算和票券形式。",
    "travelNote": "墨西哥城场适合补治安和夜间返程提示。",
    "checklist": [
      "确认票券形式",
      "准备国际支付",
      "留出返程缓冲"
    ],
    "heroImage": "/media/events/ateez-mexico-city-2026.svg",
    "ticketLinks": [
      {
        "label": "ATEEZ Official",
        "href": "https://ateez.kqent.com/",
        "type": "official"
      }
    ]
  },
  {
    "id": "gidle-paris-2026",
    "artist": "i-dle",
    "artistSlug": "gidle",
    "slug": "gidle-paris-2026",
    "city": "Paris",
    "country": "France",
    "venue": "Accor Arena",
    "startDate": "2026-11-07T20:00:00+01:00",
    "timezone": "Europe/Paris",
    "status": "announced",
    "source": "i-dle official channel",
    "sourceUrl": "https://www.cubeent.co.kr/gidle",
    "sourceConfidence": "official",
    "tags": [
      "Europe",
      "Arena",
      "Travel"
    ],
    "title": "i-dle in Paris",
    "tourName": "i-dle Tour Watch",
    "description": "i-dle 的 Paris 场会把官宣入口、购票说明、场馆交通和中文观演决策放在一起。",
    "purchaseHint": "欧洲场更看平台账户地区和支付。",
    "priceNote": "巴黎夜间返程要提前规划。",
    "travelNote": "VIP 和普通票入场时间差要看清。",
    "checklist": [
      "确认账户地区",
      "看入场时间",
      "规划返程"
    ],
    "heroImage": "/media/events/gidle-paris-2026.svg",
    "ticketLinks": [
      {
        "label": "i-dle Official",
        "href": "https://www.cubeent.co.kr/gidle",
        "type": "official"
      }
    ]
  },
  {
    "id": "red-velvet-manila-2026",
    "artist": "Red Velvet",
    "artistSlug": "red-velvet",
    "slug": "red-velvet-manila-2026",
    "city": "Manila",
    "country": "Philippines",
    "venue": "Smart Araneta Coliseum",
    "startDate": "2026-11-08T19:00:00+08:00",
    "timezone": "Asia/Manila",
    "status": "announced",
    "source": "Red Velvet official channel",
    "sourceUrl": "https://www.smtown.com/",
    "sourceConfidence": "official",
    "tags": [
      "Legacy",
      "Asia",
      "Arena"
    ],
    "title": "Red Velvet in Manila",
    "tourName": "Red Velvet Tour Watch",
    "description": "Red Velvet 的 Manila 场会把官宣入口、购票说明、场馆交通和中文观演决策放在一起。",
    "purchaseHint": "legacy 女团菲律宾场更要看票档和交通。",
    "priceNote": "不同票档福利差异值得先看。",
    "travelNote": "Araneta 一带返程不要临时决定。",
    "checklist": [
      "看福利差异",
      "确认支付",
      "规划返程"
    ],
    "heroImage": "/media/events/red-velvet-manila-2026.svg",
    "ticketLinks": [
      {
        "label": "Red Velvet Official",
        "href": "https://www.smtown.com/",
        "type": "official"
      }
    ]
  },
  {
    "id": "nct-dream-jakarta-2026",
    "artist": "NCT DREAM",
    "artistSlug": "nct-dream",
    "slug": "nct-dream-jakarta-2026",
    "city": "Jakarta",
    "country": "Indonesia",
    "venue": "Indonesia Arena",
    "startDate": "2026-11-08T19:00:00+07:00",
    "timezone": "Asia/Jakarta",
    "status": "announced",
    "source": "NCT DREAM official channel",
    "sourceUrl": "https://www.smtown.com/",
    "sourceConfidence": "official",
    "tags": [
      "Asia",
      "Arena",
      "Travel"
    ],
    "title": "NCT DREAM in Jakarta",
    "tourName": "NCT DREAM Tour Watch",
    "description": "NCT DREAM 的 Jakarta 场会把官宣入口、购票说明、场馆交通和中文观演决策放在一起。",
    "purchaseHint": "适合补印尼平台支付和手机取票规则。",
    "priceNote": "开票节奏和实名验证都值得单独说明。",
    "travelNote": "Jakarta 场馆周边交通拥堵要提前考虑。",
    "checklist": [
      "确认手机取票规则",
      "核对实名信息",
      "预留交通时间"
    ],
    "heroImage": "/media/events/nct-dream-jakarta-2026.svg",
    "ticketLinks": [
      {
        "label": "NCT DREAM Official",
        "href": "https://www.smtown.com/",
        "type": "official"
      }
    ]
  },
  {
    "id": "zico-seoul-2026",
    "artist": "ZICO",
    "artistSlug": "zico",
    "slug": "zico-seoul-2026",
    "city": "Seoul",
    "country": "South Korea",
    "venue": "SK Olympic Handball Gymnasium",
    "startDate": "2026-11-14T18:00:00+09:00",
    "timezone": "Asia/Seoul",
    "status": "announced",
    "source": "ZICO official channel",
    "sourceUrl": "https://weverse.io/zico",
    "sourceConfidence": "official",
    "tags": [
      "Solo",
      "Korea",
      "Festival"
    ],
    "title": "ZICO in Seoul",
    "tourName": "ZICO Tour Watch",
    "description": "ZICO 的 Seoul 场会把官宣入口、购票说明、场馆交通和中文观演决策放在一起。",
    "purchaseHint": "solo live 更值得先看官宣和场馆动线。",
    "priceNote": "视角、舞台段落和音场一起考虑。",
    "travelNote": "园区返程节奏提前规划。",
    "checklist": [
      "盯官宣",
      "比较视野",
      "规划返程"
    ],
    "heroImage": "/media/events/zico-seoul-2026.svg",
    "ticketLinks": [
      {
        "label": "ZICO Official",
        "href": "https://weverse.io/zico",
        "type": "official"
      }
    ]
  },
  {
    "id": "h1-key-taipei-2026",
    "artist": "H1-KEY",
    "artistSlug": "h1-key",
    "slug": "h1-key-taipei-2026",
    "city": "Taipei",
    "country": "Taiwan",
    "venue": "Legacy Taipei",
    "startDate": "2026-11-14T19:30:00+08:00",
    "timezone": "Asia/Taipei",
    "status": "announced",
    "source": "H1-KEY official channel",
    "sourceUrl": "https://www.instagram.com/h1key_official/",
    "sourceConfidence": "official",
    "tags": [
      "Theater",
      "Taiwan",
      "Travel"
    ],
    "title": "H1-KEY in Taipei",
    "tourName": "H1-KEY Tour Watch",
    "description": "H1-KEY 的 Taipei 场会把官宣入口、购票说明、场馆交通和中文观演决策放在一起。",
    "purchaseHint": "剧场场更看视角和到场时机。",
    "priceNote": "靠前站位和坐席体验差距明显。",
    "travelNote": "台北夜间返程稳定，但仍要确认末班。",
    "checklist": [
      "确认入场顺序",
      "比较前区与中区",
      "看捷运末班"
    ],
    "heroImage": "/media/events/h1-key-taipei-2026.svg",
    "ticketLinks": [
      {
        "label": "H1-KEY Official",
        "href": "https://www.instagram.com/h1key_official/",
        "type": "official"
      }
    ]
  },
  {
    "id": "stray-kids-sydney-2026",
    "artist": "Stray Kids",
    "artistSlug": "stray-kids",
    "slug": "stray-kids-sydney-2026",
    "city": "Sydney",
    "country": "Australia",
    "venue": "Qudos Bank Arena",
    "startDate": "2026-11-15T19:30:00+11:00",
    "timezone": "Australia/Sydney",
    "status": "announced",
    "source": "Stray Kids official channel",
    "sourceUrl": "https://www.straykids.jype.com/",
    "sourceConfidence": "official",
    "tags": [
      "Oceania",
      "Arena",
      "Travel"
    ],
    "title": "Stray Kids in Sydney",
    "tourName": "Stray Kids Tour Watch",
    "description": "Stray Kids 的 Sydney 场会把官宣入口、购票说明、场馆交通和中文观演决策放在一起。",
    "purchaseHint": "澳洲场要重点看 Ticketek/Ticketmaster 路线差异。",
    "priceNote": "不同入场区对视野影响较大。",
    "travelNote": "悉尼奥林匹克公园返程车次值得提前确认。",
    "checklist": [
      "准备当地票务账号",
      "核对区块视角",
      "确认返程车次"
    ],
    "heroImage": "/media/events/stray-kids-sydney-2026.svg",
    "ticketLinks": [
      {
        "label": "Stray Kids Official",
        "href": "https://www.straykids.jype.com/",
        "type": "official"
      }
    ]
  },
  {
    "id": "meovv-tokyo-2026",
    "artist": "MEOVV",
    "artistSlug": "meovv",
    "slug": "meovv-tokyo-2026",
    "city": "Tokyo",
    "country": "Japan",
    "venue": "Tokyo Garden Theater",
    "startDate": "2026-11-15T18:00:00+09:00",
    "timezone": "Asia/Tokyo",
    "status": "announced",
    "source": "MEOVV official channel",
    "sourceUrl": "https://www.instagram.com/meovv/",
    "sourceConfidence": "official",
    "tags": [
      "Japan",
      "Rookie",
      "Travel"
    ],
    "title": "MEOVV in Tokyo",
    "tourName": "MEOVV Tour Watch",
    "description": "MEOVV 的 Tokyo 场会把官宣入口、购票说明、场馆交通和中文观演决策放在一起。",
    "purchaseHint": "新团日本场要优先看抽选。",
    "priceNote": "电子票和发券方式更关键。",
    "travelNote": "丰洲区域返程路线要先确认。",
    "checklist": [
      "确认抽选",
      "核对电子票",
      "规划返程"
    ],
    "heroImage": "/media/events/meovv-tokyo-2026.svg",
    "ticketLinks": [
      {
        "label": "MEOVV Official",
        "href": "https://www.instagram.com/meovv/",
        "type": "official"
      }
    ]
  },
  {
    "id": "day6-jakarta-2026",
    "artist": "DAY6",
    "artistSlug": "day6",
    "slug": "day6-jakarta-2026",
    "city": "Jakarta",
    "country": "Indonesia",
    "venue": "Tennis Indoor Senayan",
    "startDate": "2026-11-21T19:00:00+07:00",
    "timezone": "Asia/Jakarta",
    "status": "announced",
    "source": "DAY6 official channel",
    "sourceUrl": "https://day6.jype.com/",
    "sourceConfidence": "official",
    "tags": [
      "Band",
      "Asia",
      "Travel"
    ],
    "title": "DAY6 in Jakarta",
    "tourName": "DAY6 Tour Watch",
    "description": "DAY6 的 Jakarta 场会把官宣入口、购票说明、场馆交通和中文观演决策放在一起。",
    "purchaseHint": "乐队场要优先看音场和到场时机。",
    "priceNote": "印尼平台支付和取票方式要确认。",
    "travelNote": "Senayan 区域返程时间不可低估。",
    "checklist": [
      "确认支付",
      "看音场",
      "预留返程"
    ],
    "heroImage": "/media/events/day6-jakarta-2026.svg",
    "ticketLinks": [
      {
        "label": "DAY6 Official",
        "href": "https://day6.jype.com/",
        "type": "official"
      }
    ]
  },
  {
    "id": "kickflip-seoul-2026",
    "artist": "KickFlip",
    "artistSlug": "kickflip",
    "slug": "kickflip-seoul-2026",
    "city": "Seoul",
    "country": "South Korea",
    "venue": "Yes24 Live Hall",
    "startDate": "2026-11-22T18:00:00+09:00",
    "timezone": "Asia/Seoul",
    "status": "announced",
    "source": "KickFlip official channel",
    "sourceUrl": "https://www.instagram.com/kickflip_official/",
    "sourceConfidence": "official",
    "tags": [
      "Rookie",
      "Korea",
      "Watchlist"
    ],
    "title": "KickFlip in Seoul",
    "tourName": "KickFlip Tour Watch",
    "description": "KickFlip 的 Seoul 场会把官宣入口、购票说明、场馆交通和中文观演决策放在一起。",
    "purchaseHint": "新团 live hall 更适合先看入场和站位。",
    "priceNote": "别忽略包袋和排队规则。",
    "travelNote": "广津区场次散场后转地铁很关键。",
    "checklist": [
      "确认包袋规则",
      "提早到场",
      "看排队信息"
    ],
    "heroImage": "/media/events/kickflip-seoul-2026.svg",
    "ticketLinks": [
      {
        "label": "KickFlip Official",
        "href": "https://www.instagram.com/kickflip_official/",
        "type": "official"
      }
    ]
  },
  {
    "id": "txt-los-angeles-2026",
    "artist": "TOMORROW X TOGETHER",
    "artistSlug": "txt",
    "slug": "txt-los-angeles-2026",
    "city": "Los Angeles",
    "country": "United States",
    "venue": "Kia Forum",
    "startDate": "2026-11-22T20:00:00-08:00",
    "timezone": "America/Los_Angeles",
    "status": "announced",
    "source": "TOMORROW X TOGETHER official channel",
    "sourceUrl": "https://weverse.io/txt",
    "sourceConfidence": "official",
    "tags": [
      "North America",
      "Arena",
      "Travel"
    ],
    "title": "TOMORROW X TOGETHER in Los Angeles",
    "tourName": "TOMORROW X TOGETHER Tour Watch",
    "description": "TOMORROW X TOGETHER 的 Los Angeles 场会把官宣入口、购票说明、场馆交通和中文观演决策放在一起。",
    "purchaseHint": "论坛场适合补停车、排队和周边住宿建议。",
    "priceNote": "北美 arena 场的座位性价比差异大。",
    "travelNote": "洛杉矶演出日优先地铁或提前进场。",
    "checklist": [
      "看好停车预算",
      "比较下层与上层",
      "提前出发"
    ],
    "heroImage": "/media/events/txt-los-angeles-2026.svg",
    "ticketLinks": [
      {
        "label": "TOMORROW X TOGETHER Official",
        "href": "https://weverse.io/txt",
        "type": "official"
      }
    ]
  },
  {
    "id": "plave-seoul-2026",
    "artist": "PLAVE",
    "artistSlug": "plave",
    "slug": "plave-seoul-2026",
    "city": "Seoul",
    "country": "South Korea",
    "venue": "Gocheok Sky Dome",
    "startDate": "2026-11-28T18:00:00+09:00",
    "timezone": "Asia/Seoul",
    "status": "announced",
    "source": "PLAVE official channel",
    "sourceUrl": "https://weverse.io/plave",
    "sourceConfidence": "official",
    "tags": [
      "Korea",
      "Dome",
      "Fandom"
    ],
    "title": "PLAVE in Seoul",
    "tourName": "PLAVE Tour Watch",
    "description": "PLAVE 的 Seoul 场会把官宣入口、购票说明、场馆交通和中文观演决策放在一起。",
    "purchaseHint": "高关注度场次更要盯官方。",
    "priceNote": "高尺场视角和大屏体验要一起考虑。",
    "travelNote": "散场交通缓冲要留足。",
    "checklist": [
      "盯紧官宣",
      "比较视野",
      "预留缓冲"
    ],
    "heroImage": "/media/events/plave-seoul-2026.svg",
    "ticketLinks": [
      {
        "label": "PLAVE Official",
        "href": "https://weverse.io/plave",
        "type": "official"
      }
    ]
  },
  {
    "id": "blackpink-tokyo-2026",
    "artist": "BLACKPINK",
    "artistSlug": "blackpink",
    "slug": "blackpink-tokyo-2026",
    "city": "Tokyo",
    "country": "Japan",
    "venue": "Tokyo Dome",
    "startDate": "2026-11-29T18:00:00+09:00",
    "timezone": "Asia/Tokyo",
    "status": "announced",
    "source": "BLACKPINK official channel",
    "sourceUrl": "https://www.blackpinkmusic.com/",
    "sourceConfidence": "official",
    "tags": [
      "Japan",
      "Dome",
      "BLINK"
    ],
    "title": "BLACKPINK in Tokyo",
    "tourName": "BLACKPINK Tour Watch",
    "description": "BLACKPINK 的 Tokyo 场会把官宣入口、购票说明、场馆交通和中文观演决策放在一起。",
    "purchaseHint": "日本巨蛋场的抽选和补票规则优先级最高。",
    "priceNote": "别忽视电子票和入场证件的细节。",
    "travelNote": "东京巨蛋周边酒店和返程车票都要先订。",
    "checklist": [
      "核对抽选条件",
      "确认电子票",
      "预订返程交通"
    ],
    "heroImage": "/media/events/blackpink-tokyo-2026.svg",
    "ticketLinks": [
      {
        "label": "BLACKPINK Official",
        "href": "https://www.blackpinkmusic.com/",
        "type": "official"
      }
    ]
  },
  {
    "id": "monsta-x-seoul-2026",
    "artist": "MONSTA X",
    "artistSlug": "monsta-x",
    "slug": "monsta-x-seoul-2026",
    "city": "Seoul",
    "country": "South Korea",
    "venue": "KSPO Dome",
    "startDate": "2026-11-29T18:00:00+09:00",
    "timezone": "Asia/Seoul",
    "status": "announced",
    "source": "MONSTA X official channel",
    "sourceUrl": "https://monstax-official.com/",
    "sourceConfidence": "official",
    "tags": [
      "Legacy",
      "Korea",
      "Arena"
    ],
    "title": "MONSTA X in Seoul",
    "tourName": "MONSTA X Tour Watch",
    "description": "MONSTA X 的 Seoul 场会把官宣入口、购票说明、场馆交通和中文观演决策放在一起。",
    "purchaseHint": "回归类男团场次更适合盯官方。",
    "priceNote": "区块视野和音场要同时看。",
    "travelNote": "奥林匹克公园返程别压最后一班车。",
    "checklist": [
      "盯官宣",
      "比较视野",
      "提早返程"
    ],
    "heroImage": "/media/events/monsta-x-seoul-2026.svg",
    "ticketLinks": [
      {
        "label": "MONSTA X Official",
        "href": "https://monstax-official.com/",
        "type": "official"
      }
    ]
  },
  {
    "id": "oneus-bangkok-2026",
    "artist": "ONEUS",
    "artistSlug": "oneus",
    "slug": "oneus-bangkok-2026",
    "city": "Bangkok",
    "country": "Thailand",
    "venue": "Thunder Dome",
    "startDate": "2026-12-05T19:00:00+07:00",
    "timezone": "Asia/Bangkok",
    "status": "announced",
    "source": "ONEUS official channel",
    "sourceUrl": "https://www.instagram.com/official_oneus/",
    "sourceConfidence": "official",
    "tags": [
      "Asia",
      "Arena",
      "Travel"
    ],
    "title": "ONEUS in Bangkok",
    "tourName": "ONEUS Tour Watch",
    "description": "ONEUS 的 Bangkok 场会把官宣入口、购票说明、场馆交通和中文观演决策放在一起。",
    "purchaseHint": "泰国中型 arena 场更要看交通和站席。",
    "priceNote": "支付成功率比多开几个页面更重要。",
    "travelNote": "散场交通提早锁定。",
    "checklist": [
      "确认支付方式",
      "查看站席规则",
      "预订返程"
    ],
    "heroImage": "/media/events/oneus-bangkok-2026.svg",
    "ticketLinks": [
      {
        "label": "ONEUS Official",
        "href": "https://www.instagram.com/official_oneus/",
        "type": "official"
      }
    ]
  },
  {
    "id": "v-paris-2026",
    "artist": "V",
    "artistSlug": "v",
    "slug": "v-paris-2026",
    "city": "Paris",
    "country": "France",
    "venue": "Le Zenith Paris",
    "startDate": "2026-12-05T20:00:00+01:00",
    "timezone": "Europe/Paris",
    "status": "announced",
    "source": "V official channel",
    "sourceUrl": "https://weverse.io/v",
    "sourceConfidence": "official",
    "tags": [
      "Solo",
      "Europe",
      "Travel"
    ],
    "title": "V in Paris",
    "tourName": "V Tour Watch",
    "description": "V 的 Paris 场会把官宣入口、购票说明、场馆交通和中文观演决策放在一起。",
    "purchaseHint": "欧洲 solo 场更要看账户地区和汇率。",
    "priceNote": "法国夜间返程路线要先定。",
    "travelNote": "场馆周边住宿提早订。",
    "checklist": [
      "确认账户地区",
      "规划返程",
      "提早订酒店"
    ],
    "heroImage": "/media/events/v-paris-2026.svg",
    "ticketLinks": [
      {
        "label": "V Official",
        "href": "https://weverse.io/v",
        "type": "official"
      }
    ]
  },
  {
    "id": "zerobaseone-seoul-2026",
    "artist": "ZEROBASEONE",
    "artistSlug": "zerobaseone",
    "slug": "zerobaseone-seoul-2026",
    "city": "Seoul",
    "country": "South Korea",
    "venue": "Olympic Handball Gymnasium",
    "startDate": "2026-12-06T18:00:00+09:00",
    "timezone": "Asia/Seoul",
    "status": "on_sale",
    "source": "ZEROBASEONE official channel",
    "sourceUrl": "https://zb1-official.com/",
    "sourceConfidence": "official",
    "tags": [
      "Fancon",
      "Korea",
      "Membership"
    ],
    "title": "ZEROBASEONE in Seoul",
    "tourName": "ZEROBASEONE Tour Watch",
    "description": "ZEROBASEONE 的 Seoul 场会把官宣入口、购票说明、场馆交通和中文观演决策放在一起。",
    "purchaseHint": "韩场 fancon 更适合提前研究福利票和认证规则。",
    "priceNote": "福利票常有更严格的取票条件。",
    "travelNote": "手球馆场适合补排队和安检经验。",
    "checklist": [
      "确认福利票说明",
      "核对认证规则",
      "留意入场时间"
    ],
    "heroImage": "/media/events/zerobaseone-seoul-2026.svg",
    "ticketLinks": [
      {
        "label": "ZEROBASEONE Official",
        "href": "https://zb1-official.com/",
        "type": "official"
      }
    ]
  },
  {
    "id": "jung-kook-los-angeles-2026",
    "artist": "Jung Kook",
    "artistSlug": "jung-kook",
    "slug": "jung-kook-los-angeles-2026",
    "city": "Los Angeles",
    "country": "United States",
    "venue": "Crypto.com Arena",
    "startDate": "2026-12-06T20:00:00-08:00",
    "timezone": "America/New_York",
    "status": "announced",
    "source": "Jung Kook official channel",
    "sourceUrl": "https://weverse.io/jungkook",
    "sourceConfidence": "official",
    "tags": [
      "Solo",
      "North America",
      "Arena"
    ],
    "title": "Jung Kook in Los Angeles",
    "tourName": "Jung Kook Tour Watch",
    "description": "Jung Kook 的 Los Angeles 场会把官宣入口、购票说明、场馆交通和中文观演决策放在一起。",
    "purchaseHint": "高需求 solo 场更要先准备 presale。",
    "priceNote": "Floor 和 lower bowl 的取舍要提前想。",
    "travelNote": "LA 返程别临时决定。",
    "checklist": [
      "准备 presale",
      "比较区块",
      "确认返程"
    ],
    "heroImage": "/media/events/jung-kook-los-angeles-2026.svg",
    "ticketLinks": [
      {
        "label": "Jung Kook Official",
        "href": "https://weverse.io/jungkook",
        "type": "official"
      }
    ]
  },
  {
    "id": "super-junior-taipei-2026",
    "artist": "SUPER JUNIOR",
    "artistSlug": "super-junior",
    "slug": "super-junior-taipei-2026",
    "city": "Taipei",
    "country": "Taiwan",
    "venue": "Taipei Arena",
    "startDate": "2026-12-12T19:30:00+08:00",
    "timezone": "Asia/Taipei",
    "status": "announced",
    "source": "SUPER JUNIOR official channel",
    "sourceUrl": "https://www.smtown.com/",
    "sourceConfidence": "official",
    "tags": [
      "Legacy",
      "Taiwan",
      "Arena"
    ],
    "title": "SUPER JUNIOR in Taipei",
    "tourName": "SUPER JUNIOR Tour Watch",
    "description": "SUPER JUNIOR 的 Taipei 场会把官宣入口、购票说明、场馆交通和中文观演决策放在一起。",
    "purchaseHint": "资深团台北场更适合看区块和交通。",
    "priceNote": "台北小巨蛋的正中区块通常更稳。",
    "travelNote": "住宿和捷运末班时间要提前看。",
    "checklist": [
      "看正中区块",
      "确认返程",
      "提早订酒店"
    ],
    "heroImage": "/media/events/super-junior-taipei-2026.svg",
    "ticketLinks": [
      {
        "label": "SUPER JUNIOR Official",
        "href": "https://www.smtown.com/",
        "type": "official"
      }
    ]
  },
  {
    "id": "nct-127-bangkok-2026",
    "artist": "NCT 127",
    "artistSlug": "nct-127",
    "slug": "nct-127-bangkok-2026",
    "city": "Bangkok",
    "country": "Thailand",
    "venue": "Impact Arena",
    "startDate": "2026-12-13T19:00:00+07:00",
    "timezone": "Asia/Bangkok",
    "status": "announced",
    "source": "NCT 127 official channel",
    "sourceUrl": "https://www.smtown.com/",
    "sourceConfidence": "official",
    "tags": [
      "Asia",
      "Arena",
      "Travel"
    ],
    "title": "NCT 127 in Bangkok",
    "tourName": "NCT 127 Tour Watch",
    "description": "NCT 127 的 Bangkok 场会把官宣入口、购票说明、场馆交通和中文观演决策放在一起。",
    "purchaseHint": "泰国 arena 场要把支付和返程一起考虑。",
    "priceNote": "不同区块对延伸台视野差异明显。",
    "travelNote": "Impact 周边住宿价值很高。",
    "checklist": [
      "确认支付",
      "比较视野",
      "订周边酒店"
    ],
    "heroImage": "/media/events/nct-127-bangkok-2026.svg",
    "ticketLinks": [
      {
        "label": "NCT 127 Official",
        "href": "https://www.smtown.com/",
        "type": "official"
      }
    ]
  },
  {
    "id": "xg-los-angeles-2026",
    "artist": "XG",
    "artistSlug": "xg",
    "slug": "xg-los-angeles-2026",
    "city": "Los Angeles",
    "country": "United States",
    "venue": "YouTube Theater",
    "startDate": "2026-12-13T20:00:00-08:00",
    "timezone": "America/Los_Angeles",
    "status": "announced",
    "source": "XG official channel",
    "sourceUrl": "https://xgalx.com/xg/",
    "sourceConfidence": "official",
    "tags": [
      "North America",
      "Theater",
      "GA"
    ],
    "title": "XG in Los Angeles",
    "tourName": "XG Tour Watch",
    "description": "XG 的 Los Angeles 场会把官宣入口、购票说明、场馆交通和中文观演决策放在一起。",
    "purchaseHint": "小中型场馆更需要看排队和视角。",
    "priceNote": "GA 票和坐席票体验差距明显。",
    "travelNote": "Inglewood 一带交通和散场接驳值得提前规划。",
    "checklist": [
      "确认排队时间",
      "看清 GA 规则",
      "规划散场接驳"
    ],
    "heroImage": "/media/events/xg-los-angeles-2026.svg",
    "ticketLinks": [
      {
        "label": "XG Official",
        "href": "https://xgalx.com/xg/",
        "type": "official"
      }
    ]
  },
  {
    "id": "aespa-los-angeles-2026",
    "artist": "aespa",
    "artistSlug": "aespa",
    "slug": "aespa-los-angeles-2026",
    "city": "Los Angeles",
    "country": "United States",
    "venue": "Kia Forum",
    "startDate": "2026-12-19T20:00:00-08:00",
    "timezone": "America/New_York",
    "status": "announced",
    "source": "aespa official channel",
    "sourceUrl": "https://weverse.io/aespa",
    "sourceConfidence": "official",
    "tags": [
      "North America",
      "Arena",
      "Travel"
    ],
    "title": "aespa in Los Angeles",
    "tourName": "aespa Tour Watch",
    "description": "aespa 的 Los Angeles 场会把官宣入口、购票说明、场馆交通和中文观演决策放在一起。",
    "purchaseHint": "论坛场更适合比较 floor 与 lower bowl。",
    "priceNote": "停车和网约车预算都要单独算。",
    "travelNote": "Inglewood 演出日交通拥堵明显。",
    "checklist": [
      "比较区块",
      "预留停车预算",
      "提前出发"
    ],
    "heroImage": "/media/events/aespa-los-angeles-2026.svg",
    "ticketLinks": [
      {
        "label": "aespa Official",
        "href": "https://weverse.io/aespa",
        "type": "official"
      }
    ]
  },
  {
    "id": "got7-seoul-2026",
    "artist": "GOT7",
    "artistSlug": "got7",
    "slug": "got7-seoul-2026",
    "city": "Seoul",
    "country": "South Korea",
    "venue": "KSPO Dome",
    "startDate": "2026-12-20T18:00:00+09:00",
    "timezone": "Asia/Seoul",
    "status": "announced",
    "source": "GOT7 official channel",
    "sourceUrl": "https://www.instagram.com/got7.with.igot7/",
    "sourceConfidence": "official",
    "tags": [
      "Legacy",
      "Korea",
      "Reunion"
    ],
    "title": "GOT7 in Seoul",
    "tourName": "GOT7 Tour Watch",
    "description": "GOT7 的 Seoul 场会把官宣入口、购票说明、场馆交通和中文观演决策放在一起。",
    "purchaseHint": "回归类场次优先看官宣和实名细节。",
    "priceNote": "需求高时尽量减少临场决策。",
    "travelNote": "首尔场适合提前锁住宿和返程。",
    "checklist": [
      "盯紧官宣",
      "确认实名规则",
      "提早订住宿"
    ],
    "heroImage": "/media/events/got7-seoul-2026.svg",
    "ticketLinks": [
      {
        "label": "GOT7 Official",
        "href": "https://www.instagram.com/got7.with.igot7/",
        "type": "official"
      }
    ]
  },
  {
    "id": "newjeans-seoul-2026",
    "artist": "NewJeans",
    "artistSlug": "newjeans",
    "slug": "newjeans-seoul-2026",
    "city": "Seoul",
    "country": "South Korea",
    "venue": "Jamsil Indoor Stadium",
    "startDate": "2026-12-27T18:00:00+09:00",
    "timezone": "Asia/Seoul",
    "status": "announced",
    "source": "NewJeans official channel",
    "sourceUrl": "https://weverse.io/newjeans",
    "sourceConfidence": "official",
    "tags": [
      "Korea",
      "Global",
      "Watchlist"
    ],
    "title": "NewJeans in Seoul",
    "tourName": "NewJeans Tour Watch",
    "description": "NewJeans 的 Seoul 场会把官宣入口、购票说明、场馆交通和中文观演决策放在一起。",
    "purchaseHint": "高关注艺人场次先盯官宣和实名。",
    "priceNote": "小到中型场更要提前看队列。",
    "travelNote": "蚕室返程和住宿提早安排。",
    "checklist": [
      "盯官宣",
      "确认实名",
      "提早订住宿"
    ],
    "heroImage": "/media/events/newjeans-seoul-2026.svg",
    "ticketLinks": [
      {
        "label": "NewJeans Official",
        "href": "https://weverse.io/newjeans",
        "type": "official"
      }
    ]
  }
]
